tobiiglassesctrl/__init__.py
tobiiglassesctrl/controller.py
tobiiglassesctrl-2.4.3.dist-info/LICENSE
tobiiglassesctrl-2.4.3.dist-info/METADATA
tobiiglassesctrl-2.4.3.dist-info/WHEEL
tobiiglassesctrl-2.4.3.dist-info/top_level.txt
tobiiglassesctrl-2.4.3.dist-info/RECORD
