Metadata-Version: 2.1
Name: tobiiglassesctrl
Version: 2.4.3
Summary: A Python controller for Tobii Pro Glasses 2
Home-page: https://github.com/ddetommaso/TobiiGlassesPyController/
Download-URL: https://github.com/ddetommaso/TobiiGlassesPyController/archive/2.4.3.tar.gz
Author: Davide De Tommaso
Author-email: dtmdvd@gmail.com
Keywords: eye-tracker,tobii,glasses,tobii pro glasses 2,tobii glasses,eye tracking
Classifier: Programming Language :: Python :: 3.5
Classifier: Programming Language :: Python :: 3.6
Classifier: Programming Language :: Python :: 3.7
Classifier: Programming Language :: Python :: 3.8
Classifier: Programming Language :: Python :: 3.9
License-File: LICENSE
Requires-Dist: netifaces
Requires-Dist: opencv-python ==4.2.0.32
Requires-Dist: av ==8.0.3
